{
    "md": {
        "nrOfRegions": 4,
        "nrOfTranscribedRegions": 0,
        "nrOfWordsInRegions": 0,
        "nrOfLines": 43,
        "nrOfTranscribedLines": 0,
        "nrOfWordsInLines": 0,
        "nrOfWords": 0,
        "nrOfTranscribedWords": 0,
        "nrOfCharsInLines": 0,
        "nrOfNew": 0,
        "nrOfInProgress": 3,
        "nrOfDone": 0,
        "nrOfFinal": 0,
        "nrOfGT": 0,
        "docId": 1281100,
        "title": "DIJON, Archives d\u00e9partementales de la C\u00f4te-d'Or, H(015) 288 (D\u00e9cor)",
        "uploadTimestamp": 1672778945069,
        "uploader": "genevieve.alday@gmail.com",
        "uploaderId": 131424,
        "nrOfPages": 3,
        "pageId": 51397326,
        "url": "https://files.transkribus.eu/Get?fileType=view&id=YNKQQSXSVLIAMNTDTVGYIVOG",
        "thumbUrl": "https://files.transkribus.eu/Get?fileType=thumb&id=YNKQQSXSVLIAMNTDTVGYIVOG",
        "externalId": "https://bvmm.irht.cnrs.fr/iiif/25433/manifest",
        "status": 0,
        "fimgStoreColl": "TrpDoc_DEA_1281100",
        "origDocId": 0,
        "collectionList": {
            "colList": [
                {
                    "colId": 175615,
                    "colName": "BeCoRe Fontenay",
                    "description": "created by dominique.stutzmann@irht.cnrs.fr",
                    "crowdsourcing": false,
                    "elearning": false,
                    "nrOfDocuments": 0
                }
            ]
        },
        "attributes": []
    },
    "pageList": {
        "pages": [
            {
                "pageId": 51397326,
                "docId": 1281100,
                "pageNr": 1,
                "key": "YNKQQSXSVLIAMNTDTVGYIVOG",
                "imageId": 42005012,
                "url": "https://files.transkribus.eu/Get?id=YNKQQSXSVLIAMNTDTVGYIVOG&fileType=view",
                "thumbUrl": "https://files.transkribus.eu/Get?id=YNKQQSXSVLIAMNTDTVGYIVOG&fileType=thumb",
                "md5Sum": "34788d82a6a542c47fdb4d156da6a8c5",
                "fileSize": 2306288,
                "imgFileName": "00001.jpg",
                "tsList": {
                    "transcripts": [
                        {
                            "tsId": 108580398,
                            "parentTsId": 108575439,
                            "key": "QEEMUFIFGHJYLDKFVBKQISUX",
                            "pageId": 51397326,
                            "docId": 1281100,
                            "pageNr": 1,
                            "url": "https://files.transkribus.eu/Get?id=QEEMUFIFGHJYLDKFVBKQISUX",
                            "status": "IN_PROGRESS",
                            "userName": "genevieve.alday@gmail.com",
                            "userId": 131424,
                            "timestamp": 1672827832317,
                            "toolName": "Transkribus LA 0.0.5, Model: Preset",
                            "jobId": 4078988,
                            "note": "Model: Preset",
                            "md5Sum": "457ec4c5c9d23eb1ca694b6df3d097f0",
                            "nrOfRegions": 1,
                            "nrOfTranscribedRegions": 0,
                            "nrOfWordsInRegions": 0,
                            "nrOfLines": 15,
                            "nrOfTranscribedLines": 0,
                            "nrOfWordsInLines": 0,
                            "nrOfWords": 0,
                            "nrOfTranscribedWords": 0,
                            "nrOfCharsInLines": 0,
                            "fileSize": 9434,
                            "fileName": "00001.xml"
                        },
                        {
                            "tsId": 108575439,
                            "parentTsId": 108572246,
                            "key": "UBAPSTCEKPWXBCBOLTJVOPNY",
                            "pageId": 51397326,
                            "docId": 1281100,
                            "pageNr": 1,
                            "url": "https://files.transkribus.eu/Get?id=UBAPSTCEKPWXBCBOLTJVOPNY",
                            "status": "IN_PROGRESS",
                            "userName": "genevieve.alday@gmail.com",
                            "userId": 131424,
                            "timestamp": 1672824088527,
                            "toolName": "Transkribus LA 0.0.5",
                            "jobId": 4078601,
                            "md5Sum": "554100e8d6a067ff286fedb1a1a7e786",
                            "nrOfRegions": 0,
                            "nrOfTranscribedRegions": 0,
                            "nrOfWordsInRegions": 0,
                            "nrOfLines": 0,
                            "nrOfTranscribedLines": 0,
                            "nrOfWordsInLines": 0,
                            "nrOfWords": 0,
                            "nrOfTranscribedWords": 0,
                            "nrOfCharsInLines": 0,
                            "fileSize": 629,
                            "fileName": "00001.xml"
                        },
                        {
                            "tsId": 108572246,
                            "parentTsId": 108569321,
                            "key": "OWADZOINIKAESAAUMYHIVJAW",
                            "pageId": 51397326,
                            "docId": 1281100,
                            "pageNr": 1,
                            "url": "https://files.transkribus.eu/Get?id=OWADZOINIKAESAAUMYHIVJAW",
                            "status": "IN_PROGRESS",
                            "userName": "genevieve.alday@gmail.com",
                            "userId": 131424,
                            "timestamp": 1672822978216,
                            "toolName": "Transkribus LA 0.0.5",
                            "jobId": 4078332,
                            "md5Sum": "3219d2c3bedebf8d9b19e63955595eca",
                            "nrOfRegions": 0,
                            "nrOfTranscribedRegions": 0,
                            "nrOfWordsInRegions": 0,
                            "nrOfLines": 0,
                            "nrOfTranscribedLines": 0,
                            "nrOfWordsInLines": 0,
                            "nrOfWords": 0,
                            "nrOfTranscribedWords": 0,
                            "nrOfCharsInLines": 0,
                            "fileSize": 629,
                            "fileName": "00001.xml"
                        },
                        {
                            "tsId": 108569321,
                            "parentTsId": 108555071,
                            "key": "GYBWYAMKGLPJHHCHXXZZOYPU",
                            "pageId": 51397326,
                            "docId": 1281100,
                            "pageNr": 1,
                            "url": "https://files.transkribus.eu/Get?id=GYBWYAMKGLPJHHCHXXZZOYPU",
                            "status": "IN_PROGRESS",
                            "userName": "genevieve.alday@gmail.com",
                            "userId": 131424,
                            "timestamp": 1672822494562,
                            "toolName": "Transkribus LA 0.0.5",
                            "jobId": 4078162,
                            "md5Sum": "98b700d33d983bc130e6b6896b902ce2",
                            "nrOfRegions": 0,
                            "nrOfTranscribedRegions": 0,
                            "nrOfWordsInRegions": 0,
                            "nrOfLines": 0,
                            "nrOfTranscribedLines": 0,
                            "nrOfWordsInLines": 0,
                            "nrOfWords": 0,
                            "nrOfTranscribedWords": 0,
                            "nrOfCharsInLines": 0,
                            "fileSize": 629,
                            "fileName": "00001.xml"
                        },
                        {
                            "tsId": 108555071,
                            "parentTsId": -1,
                            "key": "WSIFSOYSZGPKBCQBJOQWZNAV",
                            "pageId": 51397326,
                            "docId": 1281100,
                            "pageNr": 1,
                            "url": "https://files.transkribus.eu/Get?id=WSIFSOYSZGPKBCQBJOQWZNAV",
                            "status": "NEW",
                            "userName": "genevieve.alday@gmail.com",
                            "userId": 131424,
                            "timestamp": 1672778945069,
                            "md5Sum": "3fd91463a11d900a823d36d63465fb51",
                            "nrOfRegions": 0,
                            "nrOfTranscribedRegions": 0,
                            "nrOfWordsInRegions": 0,
                            "nrOfLines": 0,
                            "nrOfTranscribedLines": 0,
                            "nrOfWordsInLines": 0,
                            "nrOfWords": 0,
                            "nrOfTranscribedWords": 0,
                            "nrOfCharsInLines": 0,
                            "fileSize": 611,
                            "fileName": "00001.xml"
                        }
                    ]
                },
                "width": 3564,
                "height": 5000,
                "created": "2023-01-03T21:49:05.155+01:00",
                "indexed": true,
                "imageVersions": {
                    "imageVersions": []
                },
                "tagsStored": "2023-01-04T11:23:53.291+01:00",
                "lastModified": "2023-01-04T11:23:53.276+01:00",
                "lastIndexed": "2023-01-04T11:23:57.898+01:00"
            },
            {
                "pageId": 51397327,
                "docId": 1281100,
                "pageNr": 2,
                "key": "QFDIJVICAZVJQKWAWMSNFUUK",
                "imageId": 42005013,
                "url": "https://files.transkribus.eu/Get?id=QFDIJVICAZVJQKWAWMSNFUUK&fileType=view",
                "thumbUrl": "https://files.transkribus.eu/Get?id=QFDIJVICAZVJQKWAWMSNFUUK&fileType=thumb",
                "md5Sum": "33cf08e5d772ab8d8498b9b09df2445f",
                "fileSize": 2792193,
                "imgFileName": "00002.jpg",
                "tsList": {
                    "transcripts": [
                        {
                            "tsId": 108580401,
                            "parentTsId": 108575442,
                            "key": "XFMPXAXBYNKMHCQEUCTXYEFV",
                            "pageId": 51397327,
                            "docId": 1281100,
                            "pageNr": 2,
                            "url": "https://files.transkribus.eu/Get?id=XFMPXAXBYNKMHCQEUCTXYEFV",
                            "status": "IN_PROGRESS",
                            "userName": "genevieve.alday@gmail.com",
                            "userId": 131424,
                            "timestamp": 1672827833323,
                            "toolName": "Transkribus LA 0.0.5, Model: Preset",
                            "jobId": 4078988,
                            "note": "Model: Preset",
                            "md5Sum": "387c889385eff77dd70ba5dcb084c441",
                            "nrOfRegions": 1,
                            "nrOfTranscribedRegions": 0,
                            "nrOfWordsInRegions": 0,
                            "nrOfLines": 26,
                            "nrOfTranscribedLines": 0,
                            "nrOfWordsInLines": 0,
                            "nrOfWords": 0,
                            "nrOfTranscribedWords": 0,
                            "nrOfCharsInLines": 0,
                            "fileSize": 50391,
                            "fileName": "00002.xml"
                        },
                        {
                            "tsId": 108575442,
                            "parentTsId": 108572252,
                            "key": "BAXEXSEQIGOZVPNQIIDOYXOQ",
                            "pageId": 51397327,
                            "docId": 1281100,
                            "pageNr": 2,
                            "url": "https://files.transkribus.eu/Get?id=BAXEXSEQIGOZVPNQIIDOYXOQ",
                            "status": "IN_PROGRESS",
                            "userName": "genevieve.alday@gmail.com",
                            "userId": 131424,
                            "timestamp": 1672824092167,
                            "toolName": "Transkribus LA 0.0.5",
                            "jobId": 4078601,
                            "md5Sum": "5f7ef2be6d0324c300f3e7ee03e3d6a8",
                            "nrOfRegions": 0,
                            "nrOfTranscribedRegions": 0,
                            "nrOfWordsInRegions": 0,
                            "nrOfLines": 0,
                            "nrOfTranscribedLines": 0,
                            "nrOfWordsInLines": 0,
                            "nrOfWords": 0,
                            "nrOfTranscribedWords": 0,
                            "nrOfCharsInLines": 0,
                            "fileSize": 629,
                            "fileName": "00002.xml"
                        },
                        {
                            "tsId": 108572252,
                            "parentTsId": 108569324,
                            "key": "YBYNXZNTWIQUVZFXKTGAHFHG",
                            "pageId": 51397327,
                            "docId": 1281100,
                            "pageNr": 2,
                            "url": "https://files.transkribus.eu/Get?id=YBYNXZNTWIQUVZFXKTGAHFHG",
                            "status": "IN_PROGRESS",
                            "userName": "genevieve.alday@gmail.com",
                            "userId": 131424,
                            "timestamp": 1672822978993,
                            "toolName": "Transkribus LA 0.0.5",
                            "jobId": 4078332,
                            "md5Sum": "ef1e1774f60658ae5b4fdab99c1cc183",
                            "nrOfRegions": 0,
                            "nrOfTranscribedRegions": 0,
                            "nrOfWordsInRegions": 0,
                            "nrOfLines": 0,
                            "nrOfTranscribedLines": 0,
                            "nrOfWordsInLines": 0,
                            "nrOfWords": 0,
                            "nrOfTranscribedWords": 0,
                            "nrOfCharsInLines": 0,
                            "fileSize": 629,
                            "fileName": "00002.xml"
                        },
                        {
                            "tsId": 108569324,
                            "parentTsId": 108555072,
                            "key": "NPPRQQNGJMPEVGVLTKJVGTFF",
                            "pageId": 51397327,
                            "docId": 1281100,
                            "pageNr": 2,
                            "url": "https://files.transkribus.eu/Get?id=NPPRQQNGJMPEVGVLTKJVGTFF",
                            "status": "IN_PROGRESS",
                            "userName": "genevieve.alday@gmail.com",
                            "userId": 131424,
                            "timestamp": 1672822495028,
                            "toolName": "Transkribus LA 0.0.5",
                            "jobId": 4078162,
                            "md5Sum": "f700f7f589a6efe775165ab8d0c8ad32",
                            "nrOfRegions": 0,
                            "nrOfTranscribedRegions": 0,
                            "nrOfWordsInRegions": 0,
                            "nrOfLines": 0,
                            "nrOfTranscribedLines": 0,
                            "nrOfWordsInLines": 0,
                            "nrOfWords": 0,
                            "nrOfTranscribedWords": 0,
                            "nrOfCharsInLines": 0,
                            "fileSize": 629,
                            "fileName": "00002.xml"
                        },
                        {
                            "tsId": 108555072,
                            "parentTsId": -1,
                            "key": "PDPJAFWTBOJARYHKDAFPCFTC",
                            "pageId": 51397327,
                            "docId": 1281100,
                            "pageNr": 2,
                            "url": "https://files.transkribus.eu/Get?id=PDPJAFWTBOJARYHKDAFPCFTC",
                            "status": "NEW",
                            "userName": "genevieve.alday@gmail.com",
                            "userId": 131424,
                            "timestamp": 1672778945069,
                            "md5Sum": "273ca1216e8b9e10aa3381d25db5fd95",
                            "nrOfRegions": 0,
                            "nrOfTranscribedRegions": 0,
                            "nrOfWordsInRegions": 0,
                            "nrOfLines": 0,
                            "nrOfTranscribedLines": 0,
                            "nrOfWordsInLines": 0,
                            "nrOfWords": 0,
                            "nrOfTranscribedWords": 0,
                            "nrOfCharsInLines": 0,
                            "fileSize": 611,
                            "fileName": "00002.xml"
                        }
                    ]
                },
                "width": 5000,
                "height": 3728,
                "created": "2023-01-03T21:49:06.017+01:00",
                "indexed": true,
                "imageVersions": {
                    "imageVersions": []
                },
                "tagsStored": "2023-01-04T11:23:53.646+01:00",
                "lastModified": "2023-01-04T11:23:53.633+01:00",
                "lastIndexed": "2023-01-04T11:23:58.366+01:00"
            },
            {
                "pageId": 51397328,
                "docId": 1281100,
                "pageNr": 3,
                "key": "RVLJFIWYDGRSLZYPYHJZFDMV",
                "imageId": 42005014,
                "url": "https://files.transkribus.eu/Get?id=RVLJFIWYDGRSLZYPYHJZFDMV&fileType=view",
                "thumbUrl": "https://files.transkribus.eu/Get?id=RVLJFIWYDGRSLZYPYHJZFDMV&fileType=thumb",
                "md5Sum": "dea5b2b1153b03b982ab29bf02131158",
                "fileSize": 2528869,
                "imgFileName": "00003.jpg",
                "tsList": {
                    "transcripts": [
                        {
                            "tsId": 108580402,
                            "parentTsId": 108575445,
                            "key": "NWUOIXTTTYXOTZTMJLZBYFCD",
                            "pageId": 51397328,
                            "docId": 1281100,
                            "pageNr": 3,
                            "url": "https://files.transkribus.eu/Get?id=NWUOIXTTTYXOTZTMJLZBYFCD",
                            "status": "IN_PROGRESS",
                            "userName": "genevieve.alday@gmail.com",
                            "userId": 131424,
                            "timestamp": 1672827833665,
                            "toolName": "Transkribus LA 0.0.5, Model: Preset",
                            "jobId": 4078988,
                            "note": "Model: Preset",
                            "md5Sum": "f1dd518d336fa231f772082fe5231f29",
                            "nrOfRegions": 2,
                            "nrOfTranscribedRegions": 0,
                            "nrOfWordsInRegions": 0,
                            "nrOfLines": 2,
                            "nrOfTranscribedLines": 0,
                            "nrOfWordsInLines": 0,
                            "nrOfWords": 0,
                            "nrOfTranscribedWords": 0,
                            "nrOfCharsInLines": 0,
                            "fileSize": 2494,
                            "fileName": "00003.xml"
                        },
                        {
                            "tsId": 108575445,
                            "parentTsId": 108572255,
                            "key": "HPNCKAJVTQOOAEZWQLQXBQHI",
                            "pageId": 51397328,
                            "docId": 1281100,
                            "pageNr": 3,
                            "url": "https://files.transkribus.eu/Get?id=HPNCKAJVTQOOAEZWQLQXBQHI",
                            "status": "IN_PROGRESS",
                            "userName": "genevieve.alday@gmail.com",
                            "userId": 131424,
                            "timestamp": 1672824092689,
                            "toolName": "Transkribus LA 0.0.5",
                            "jobId": 4078601,
                            "md5Sum": "51211ee936c39977e859bf05d1b5d6f2",
                            "nrOfRegions": 0,
                            "nrOfTranscribedRegions": 0,
                            "nrOfWordsInRegions": 0,
                            "nrOfLines": 0,
                            "nrOfTranscribedLines": 0,
                            "nrOfWordsInLines": 0,
                            "nrOfWords": 0,
                            "nrOfTranscribedWords": 0,
                            "nrOfCharsInLines": 0,
                            "fileSize": 629,
                            "fileName": "00003.xml"
                        },
                        {
                            "tsId": 108572255,
                            "parentTsId": 108569326,
                            "key": "OWITILIEPFGGJIHFUBLMCDUP",
                            "pageId": 51397328,
                            "docId": 1281100,
                            "pageNr": 3,
                            "url": "https://files.transkribus.eu/Get?id=OWITILIEPFGGJIHFUBLMCDUP",
                            "status": "IN_PROGRESS",
                            "userName": "genevieve.alday@gmail.com",
                            "userId": 131424,
                            "timestamp": 1672822979285,
                            "toolName": "Transkribus LA 0.0.5",
                            "jobId": 4078332,
                            "md5Sum": "19d7676528bc9a70abd3e24d379d7db0",
                            "nrOfRegions": 0,
                            "nrOfTranscribedRegions": 0,
                            "nrOfWordsInRegions": 0,
                            "nrOfLines": 0,
                            "nrOfTranscribedLines": 0,
                            "nrOfWordsInLines": 0,
                            "nrOfWords": 0,
                            "nrOfTranscribedWords": 0,
                            "nrOfCharsInLines": 0,
                            "fileSize": 629,
                            "fileName": "00003.xml"
                        },
                        {
                            "tsId": 108569326,
                            "parentTsId": 108555073,
                            "key": "HWDHEFULJAAZWFQHIEEGUPDL",
                            "pageId": 51397328,
                            "docId": 1281100,
                            "pageNr": 3,
                            "url": "https://files.transkribus.eu/Get?id=HWDHEFULJAAZWFQHIEEGUPDL",
                            "status": "IN_PROGRESS",
                            "userName": "genevieve.alday@gmail.com",
                            "userId": 131424,
                            "timestamp": 1672822495360,
                            "toolName": "Transkribus LA 0.0.5",
                            "jobId": 4078162,
                            "md5Sum": "819c2ce78624c790e7ace259431da040",
                            "nrOfRegions": 0,
                            "nrOfTranscribedRegions": 0,
                            "nrOfWordsInRegions": 0,
                            "nrOfLines": 0,
                            "nrOfTranscribedLines": 0,
                            "nrOfWordsInLines": 0,
                            "nrOfWords": 0,
                            "nrOfTranscribedWords": 0,
                            "nrOfCharsInLines": 0,
                            "fileSize": 629,
                            "fileName": "00003.xml"
                        },
                        {
                            "tsId": 108555073,
                            "parentTsId": -1,
                            "key": "WZYTDOEUBDSNIHUHSCMXHSQF",
                            "pageId": 51397328,
                            "docId": 1281100,
                            "pageNr": 3,
                            "url": "https://files.transkribus.eu/Get?id=WZYTDOEUBDSNIHUHSCMXHSQF",
                            "status": "NEW",
                            "userName": "genevieve.alday@gmail.com",
                            "userId": 131424,
                            "timestamp": 1672778945069,
                            "md5Sum": "0885e555094fa09a105683c016c9cf12",
                            "nrOfRegions": 0,
                            "nrOfTranscribedRegions": 0,
                            "nrOfWordsInRegions": 0,
                            "nrOfLines": 0,
                            "nrOfTranscribedLines": 0,
                            "nrOfWordsInLines": 0,
                            "nrOfWords": 0,
                            "nrOfTranscribedWords": 0,
                            "nrOfCharsInLines": 0,
                            "fileSize": 611,
                            "fileName": "00003.xml"
                        }
                    ]
                },
                "width": 5000,
                "height": 3716,
                "created": "2023-01-03T21:49:06.976+01:00",
                "indexed": true,
                "imageVersions": {
                    "imageVersions": []
                },
                "tagsStored": "2023-01-04T11:23:54.01+01:00",
                "lastModified": "2023-01-04T11:23:53.998+01:00",
                "lastIndexed": "2023-01-04T11:23:58.358+01:00"
            }
        ]
    },
    "collection": {
        "colId": 175615,
        "colName": "BeCoRe Fontenay",
        "description": "created by dominique.stutzmann@irht.cnrs.fr",
        "crowdsourcing": false,
        "elearning": false,
        "pageId": 51024238,
        "url": "https://files.transkribus.eu/Get?fileType=view&id=EIDAGCEVKRXBXMHNZNODJELY",
        "thumbUrl": "https://files.transkribus.eu/Get?fileType=thumb&id=EIDAGCEVKRXBXMHNZNODJELY",
        "nrOfDocuments": 0,
        "accountingStatus": 1
    },
    "edDeclList": []
}